source/slv_i2c_fsm.v
module slv_i2c_fsm
    #(parameter DATA_SZ = 8) // data widht              
    (CLK, RST_n, I_SCL, I_SDA, I_RS_IO_SCL, I_FL_IO_SCL, I_RS_IO_SDA, I_FL_IO_SDA, I_ACK, I_MDL_LW_IO_SCL, I_DATA_WR,
     O_ADDR_SLV, O_RW, O_DATA_RD, O_BUSY, O_DATA_VL, O_SDA, O_ADDR_REG, O_CH_CNCT);
     

//--------------------------------------------------------------------------      
    localparam CNT_BIT_DATA_SZ = $clog2(DATA_SZ) + 1; // data width of bit counter  
//  description states FSM
    localparam ST_SZ     = 9; // number of states FSM
    (* syn_encoding = "one-hot" *) reg [ST_SZ-1:0] st; // current state of FSM
    localparam IDLE      = 0; // default state
    localparam START     = 1; // start of a transaction on the I2C bus
    localparam COMM_MSTR = 2; // trasmitter of command from master to the slave
    localparam ACK_COMM  = 3; // ACK from the slave to the master
    localparam WR        = 4; // writing data from the slave to the master
    localparam RD        = 6; // reading data from the master to the slave
    localparam MSTR_ACK  = 7; // ACK bit data from master
    localparam ADDR_REG  = 8; // addr_reg in the slave
    localparam ACK_DATA  = 9; // 
//  input signals
    input wire               CLK;         // clock 50 MHz
    input wire               RST_n;       // asynchronous reset_n
    input wire               I_SCL;       // serial clock from the master
    input wire               I_SDA;       // serial data from the master
    input wire               I_RS_IO_SCL; // rising edge of IO_SCL
    input wire               I_FL_IO_SCL; // falling edge of IO_SCL
    input wire               I_RS_IO_SDA; // rising edge of IO_SDA
    input wire               I_FL_IO_SDA; // falling edge of IO_SDA
    input wire               I_ACK;       // ACK from the slave to the master
    input wire               I_MDL_LW_IO_SCL; // enable the slave to transmit a bit
    input wire [DATA_SZ-1:0] I_DATA_WR;   // data for writing to the master
//  output signals
    output reg [DATA_SZ-2:0] O_ADDR_SLV; // addr the slave
    output reg [DATA_SZ-1:0] O_ADDR_REG; // addr the slave
    output reg               O_RW;       // RW
    output reg [DATA_SZ-1:0] O_DATA_RD;  // read data from the master
    output reg               O_SDA;      // O_SDA from the slave to the master
    output reg               O_BUSY;
    output reg               O_DATA_VL;
    output reg               O_CH_CNCT;  // check connection
//  internal signals 
    reg [ST_SZ-1:0]           nx_st;           // next state of FSM 
    reg [DATA_SZ-2:0]         nx_o_addr_slv;   // next addr the slave
    reg                       nx_o_rw;         // next RW
    reg [DATA_SZ-1:0]         nx_o_addr_reg;   // next addr_reg in the slave
    reg [DATA_SZ-1:0]         nx_o_data_rd;    // next read data from the master
    reg [DATA_SZ-1:0]         buff_rd;         // data buffer of the slave
    reg [DATA_SZ-1:0]         nx_buff_rd;      // next data buffer of the slave    
    reg [CNT_BIT_DATA_SZ-1:0] cnt_bit_data;    // data bit counter
    reg [CNT_BIT_DATA_SZ-1:0] nx_cnt_bit_data; // next data bit counter
    reg                       nx_o_sda;        // next O_SDA from the slave to the mastere
    reg [DATA_SZ-1:0]         comm_slv;        // latched address and read/write
    reg [DATA_SZ-1:0]         nx_comm_slv;     // next latched address and read/write 
    reg                       go;
    reg                       nx_go;
    reg                       nx_o_busy;
    reg                       nx_o_data_vl;
    reg [DATA_SZ-1:0]         buff_wr;
    reg [DATA_SZ-1:0]         nx_buff_wr;
    reg                       nx_o_ch_cnct;  // check connection
    reg [DATA_SZ-1:0]         pr_comm_slv;
    reg [DATA_SZ-1:0]         pr_addr_reg;
    reg [DATA_SZ-1:0]         nx_pr_comm_slv;
    reg [DATA_SZ-1:0]         nx_pr_addr_reg;
    reg [DATA_SZ-1:0]         addr_reg_offset;
    reg [DATA_SZ-1:0]         nx_addr_reg_offset;
    reg                       ack_from_slave;
    reg                       nx_ack_from_slave;
 
//  determining next state of FSM and signals
    always @(*) begin
        nx_st = st;
        nx_buff_rd = buff_rd; 
        nx_cnt_bit_data = cnt_bit_data;
        nx_o_data_rd = O_DATA_RD;
        nx_o_addr_slv = O_ADDR_SLV;
        nx_o_rw = O_RW;
        nx_o_sda = O_SDA;
        nx_comm_slv = comm_slv;
        nx_go = go;
        nx_o_busy = O_BUSY;
        nx_o_data_vl = O_DATA_VL;
        nx_buff_wr = buff_wr;
        nx_o_addr_reg = O_ADDR_REG;
        nx_o_ch_cnct = O_CH_CNCT;
        nx_pr_comm_slv = pr_comm_slv;
        nx_pr_addr_reg = pr_addr_reg;
        nx_addr_reg_offset = addr_reg_offset;
        nx_ack_from_slave = ack_from_slave;
        case (st)    
            IDLE     :  begin
                            if (I_FL_IO_SDA & I_SCL)
                                begin
                                    nx_o_busy = 1'b1;
                                    nx_st = START;
                                end
                        end
            START    :  begin   
                            if (I_RS_IO_SCL)
                                begin
                                    nx_cnt_bit_data = DATA_SZ - 1'b1;
                                    nx_buff_rd = {nx_buff_rd[DATA_SZ-2:0], I_SDA};
                                    nx_st = COMM_MSTR;
                                end
                        end
            COMM_MSTR : begin
                            if (I_RS_IO_SCL)
                                begin
                                    nx_buff_rd = {nx_buff_rd[DATA_SZ-2:0], I_SDA};
                                    nx_cnt_bit_data = cnt_bit_data - 1'b1;
                                end
                            if (&(!cnt_bit_data))
                                begin
                                    // nx_o_rw = buff_rd[0];
                                    nx_comm_slv = buff_rd;
                                    if ({pr_comm_slv[DATA_SZ-1:1], ~pr_comm_slv[0]} == buff_rd)
                                        begin
                                            nx_o_rw = 1'b1;
                                            nx_o_addr_slv = buff_rd[DATA_SZ-1:1];
                                            nx_o_addr_reg = pr_addr_reg;
                                            nx_o_data_vl = 1'b1;
                                        end
                                    else
                                        begin
                                            nx_o_addr_slv = buff_rd[DATA_SZ-1:1];
                                            nx_o_rw = buff_rd[0];
                                            nx_o_ch_cnct = 1'b1;
                                        end
                                    if (I_MDL_LW_IO_SCL)
                                        begin
                                            nx_cnt_bit_data = DATA_SZ - 1'b1;
                                            nx_o_sda = I_ACK;
                                            nx_ack_from_slave = I_ACK;
                                            nx_go = 1'b1;
                                            nx_o_ch_cnct = 1'b0;
                                            nx_o_data_vl = 1'b0;
                                            nx_st = ACK_COMM;
                                        end
                                end
                        end
            ACK_COMM :  begin
                            if (I_MDL_LW_IO_SCL)
                                begin
                                    nx_go = 1'b0;
                                    if (comm_slv[0])
                                        begin
                                            nx_buff_wr = {I_DATA_WR[DATA_SZ-2:0], 1'b0};
                                            nx_o_sda = I_DATA_WR[DATA_SZ-1];
                                            nx_st = WR;
                                        end
                                    else nx_o_sda = 1'b1; 
                                end
                            if (I_RS_IO_SDA & I_SCL)
                                begin
                                    nx_o_busy = 1'b0;
                                    // nx_pr_comm_slv = comm_slv;
                                    nx_st = IDLE;
                                end
                            if (I_FL_IO_SCL & !go)
                                begin
                                    nx_buff_rd = {buff_rd[DATA_SZ-2:0], I_SDA};
                                    nx_st = ADDR_REG;
                                    // nx_cnt_bit_data = DATA_SZ - 1'b1;
                                end
                        end
            ADDR_REG :  begin
                            if (I_RS_IO_SCL)
                                begin
                                    nx_buff_rd = {nx_buff_rd[DATA_SZ-2:0], I_SDA};
                                    nx_cnt_bit_data = cnt_bit_data - 1'b1;
                                end
                            if (&(!cnt_bit_data))
                                begin
                                    // nx_o_rw = 1'b0;
                                    // nx_o_addr_slv = comm_slv[DATA_SZ-1:1];
                                    // nx_o_data_vl = 1'b1;                                    
                                    nx_o_addr_reg = buff_rd;
                                    nx_addr_reg_offset = {DATA_SZ{1'b0}};
                                    if (I_MDL_LW_IO_SCL)
                                        begin
                                            nx_cnt_bit_data = DATA_SZ - 1'b1;
                                            nx_o_sda = ack_from_slave;
                                            nx_go = 1'b1;
                                            nx_st = ACK_DATA;
                                            // nx_o_data_vl = 1'b0; 
                                        end
                                end
                        end
            ACK_DATA :  begin
                            if (I_MDL_LW_IO_SCL)
                                begin
                                    nx_go = 1'b0;
                                    if (comm_slv[0])
                                        begin
                                            nx_buff_wr = {I_DATA_WR[DATA_SZ-2:0], 1'b0};
                                            nx_o_sda = I_DATA_WR[DATA_SZ-1];
                                            nx_st = WR;
                                        end
                                    else nx_o_sda = 1'b1; 
                                end
                            if (I_RS_IO_SDA & I_SCL)
                                begin
                                    nx_o_busy = 1'b0;
                                    // nx_o_data_vl = 1'b0;
                                    nx_st = IDLE;
                                    nx_pr_addr_reg = O_ADDR_REG;
                                    nx_pr_comm_slv = comm_slv;
                                end
                            if (I_FL_IO_SCL & !go)
                                begin
                                    nx_buff_rd = {buff_rd[DATA_SZ-2:0], I_SDA};
                                    nx_st = RD;
                                    // nx_cnt_bit_data = DATA_SZ - 1'b1;
                                end
                        end       
            
            RD       :  begin
                            if (I_RS_IO_SCL)
                                begin
                                    nx_buff_rd = {nx_buff_rd[DATA_SZ-2:0], I_SDA};
                                    nx_cnt_bit_data = cnt_bit_data - 1'b1;
                                end
                            if (&(!cnt_bit_data))
                                begin
                                    nx_o_addr_reg = &(!addr_reg_offset) ? O_ADDR_REG : addr_reg_offset;
                                    nx_o_data_rd = buff_rd;
                                    nx_o_data_vl = 1'b1;
                                    if (I_MDL_LW_IO_SCL)
                                        begin
                                            nx_cnt_bit_data = DATA_SZ - 1'b1;
                                            nx_o_sda = ack_from_slave;
                                            nx_go = 1'b1;
                                            nx_o_data_vl = 1'b0;
                                            nx_st = ACK_DATA;
                                            nx_addr_reg_offset = O_ADDR_REG + 1'b1;
                                        end
                                end
                        end
            
            
            
            
            
            WR       :  begin
                            if (I_MDL_LW_IO_SCL)
                                begin
                                    nx_o_sda = buff_wr[DATA_SZ-1];
                                    nx_buff_wr = {buff_wr[DATA_SZ-2:0], 1'b0};
                                    nx_cnt_bit_data = cnt_bit_data - 1'b1;
                                end
                            if (&(!cnt_bit_data))
                                begin
                                    if (I_MDL_LW_IO_SCL)
                                        begin
                                            nx_cnt_bit_data = DATA_SZ - 1'b1;
                                            nx_o_sda = 1'b1;
                                            nx_st = MSTR_ACK;
                                        end
                                end
                        end
            MSTR_ACK :  begin
                            if (I_RS_IO_SCL)
                                begin
                                    if (I_SDA)
                                        begin
                                            nx_o_busy = 1'b0;
                                            nx_st = IDLE;
                                        end
                                    else
                                        begin
                                            nx_o_addr_reg = O_ADDR_REG + 1'b1;
                                            nx_o_data_vl = 1'b1;                                        
                                        end  
                                end
                            if (I_MDL_LW_IO_SCL)
                                begin
                                    nx_buff_wr = {I_DATA_WR[DATA_SZ-2:0], 1'b0};
                                    nx_o_sda = I_DATA_WR[DATA_SZ-1];
                                    nx_o_data_vl = 1'b0;
                                    nx_st = WR;
                                end
                        end
            default  :  begin
                            nx_st = IDLE;
                            nx_o_sda = 1'b1;
                            nx_o_busy = 1'b0;
                            nx_o_data_vl = 1'b0;
                            pr_comm_slv = {DATA_SZ{1'b0}};
                        end 
        endcase
    end

//  latching the next state of FSM and signals, every clock
    always @(posedge CLK or negedge RST_n) begin
        if (!RST_n) 
            begin
                st       <= IDLE;
                buff_rd  <= {DATA_SZ{1'b0}};
                cnt_bit_data <= {CNT_BIT_DATA_SZ{1'b0}};
                O_DATA_RD <= {DATA_SZ{1'b0}};
                O_ADDR_SLV <= {DATA_SZ-1{1'b0}};
                O_RW <= 1'b0;
                O_SDA    <= 1'b1;
                comm_slv <= {DATA_SZ{1'b0}};
                go <= 1'b0;
                O_BUSY <= 1'b0;
                O_DATA_VL <= 1'b0;
                buff_wr <= {DATA_SZ{1'b0}};
                O_ADDR_REG <= {DATA_SZ{1'b0}};
                O_CH_CNCT <= 1'b0;
                pr_comm_slv <= {DATA_SZ{1'b0}};
                pr_addr_reg <= {DATA_SZ{1'b0}}; 
                addr_reg_offset <= {DATA_SZ{1'b0}};
                ack_from_slave <= 1'b1;
            end
        else 
            begin
                st       <= nx_st;
                buff_rd  <= nx_buff_rd;
                cnt_bit_data <= nx_cnt_bit_data;
                O_DATA_RD    <= nx_o_data_rd;
                O_ADDR_SLV <= nx_o_addr_slv;
                O_RW <= nx_o_rw;
                O_SDA    <= nx_o_sda; 
                comm_slv <= nx_comm_slv;
                go <= nx_go;
                O_BUSY <= nx_o_busy;
                O_DATA_VL <= nx_o_data_vl;
                buff_wr <= nx_buff_wr;
                O_ADDR_REG <= nx_o_addr_reg;
                O_CH_CNCT <= nx_o_ch_cnct;
                pr_comm_slv <= nx_pr_comm_slv;
                pr_addr_reg <= nx_pr_addr_reg;
                addr_reg_offset <= nx_addr_reg_offset;
                ack_from_slave <= nx_ack_from_slave;
            end
    end


endmodule

source/def_freq_i2c.v
module def_freq_i2c
    #(parameter FPGA_CLK = 50_000_000,         // FPGA frequency 50 MHz
      parameter I2C_CLK  = 100_000,            // minimum frequency of I2C bus (100 KHz)
      parameter NUM_CYC  = FPGA_CLK / I2C_CLK, // maximum number of cycles
      parameter CNT_SZ   = $clog2(NUM_CYC))    // width of clock counter
    (CLK, RST_n, I_SCL, I_RS_IO_SCL, I_FL_IO_SCL, 
     O_MDL_LW_IO_SCL, O_MDL_HG_IO_SCL);
    
    
//  input signals
    input wire CLK;         // clock 50 MHz
    input wire RST_n;       // asynchronous reset_n
    input wire I_SCL;       // serial clock from the I2C_master'
    input wire I_RS_IO_SCL; // rising edge of IO_SCL
    input wire I_FL_IO_SCL; // falling edge of IO_SCL
//  output signals
    output reg O_MDL_LW_IO_SCL; // middle of HIGH IO_SCL
    output reg O_MDL_HG_IO_SCL; // middle of LOW IO_SCL
//  internal signals
    reg [CNT_SZ-1:0] cnt;    // clock counter
    reg [CNT_SZ-1:0] sv_cnt; // current value of the clock counter
    wire             en_str; // enable strobe O_MDL_LW_IO_SCL or O_MDL_HG_IO_SCL
    
//--------------------------------------------------------------------------
    assign en_str = cnt == (sv_cnt >> 1'b1) & (cnt > 1'b0);
    
//--------------------------------------------------------------------------    
    always @(posedge CLK or negedge RST_n) begin
        if (!RST_n)
            begin
                cnt <= {CNT_SZ{1'b0}};
                sv_cnt <= {CNT_SZ{1'b0}};
                O_MDL_LW_IO_SCL <= 1'b0;
                O_MDL_HG_IO_SCL <= 1'b0;
            end
        else  
            begin
                cnt <= I_FL_IO_SCL || I_RS_IO_SCL ? {CNT_SZ{1'b0}} : cnt + 1'b1;
                sv_cnt <= I_FL_IO_SCL ? cnt : sv_cnt;
                O_MDL_LW_IO_SCL <= !I_SCL & en_str ? 1'b1 : 1'b0;
                O_MDL_HG_IO_SCL <= I_SCL & en_str ? 1'b1 : 1'b0;
            end
    end


endmodule

source/top_slv_i2c.v
module top_slv_i2c
    #(parameter FPGA_CLK = 50_000_000,  // FPGA frequency 50 MHz
      parameter I2C_CLK  = 100_000,     // I2C bus frequency 400 KHz
      parameter DATA_SZ  = 8)           // data widht
    (CLK, RST_n, I_ACK, I_SCL, I_DATA_WR,
     O_ADDR_SLV, O_RW, O_DATA_RD, O_BUSY, O_DATA_VL, O_ADDR_REG, O_CH_CNCT,
     IO_SDA);

    
//--------------------------------------------------------------------------    
//  input signals
    input wire                CLK;       // clock 50 MHz
    input wire                RST_n;     // asynchronous reset_n
    input wire I_SCL; // serial clock I2C bus 
    input wire I_ACK;
    input wire [DATA_SZ-1:0] I_DATA_WR;   // data for writing to the master    
//  output signals
    output wire [DATA_SZ-2:0] O_ADDR_SLV; // addr the slave
    output wire               O_RW;       // RW
    output wire [DATA_SZ-1:0] O_DATA_RD;  // read data from the master
    output wire               O_BUSY;
    output wire               O_DATA_VL;
    output wire [DATA_SZ-1:0] O_ADDR_REG; // addr the slave
    output wire               O_CH_CNCT;  // check connection
//  bidirectional signals
    inout wire IO_SDA; // serial data I2C bus
//  internal signals        
    wire               mdl_lw_io_scl;     // enable I2_C slave to transmit a bit    
    wire               mdl_hg_io_scl;     
    wire sda;
    wire sda_out;
    reg cr_sda;
    reg pr_sda;
    wire rs_sda;
    wire fl_sda;
    reg cr_scl;
    reg pr_scl;
    wire rs_scl;
    wire fl_scl;
    
//--------------------------------------------------------------------------       
    assign sda    = IO_SDA;
    assign IO_SDA = sda_out ? 1'bz : 1'b0;
    assign rs_sda = cr_sda & !pr_sda;
    assign fl_sda = !cr_sda & pr_sda;
    assign rs_scl = cr_scl & !pr_scl;
    assign fl_scl = !cr_scl & pr_scl;

//--------------------------------------------------------------------------       
    always @(posedge CLK or negedge RST_n) begin
        if (!RST_n)
            begin
                cr_scl <= 1'b0;
                pr_scl <= 1'b0;
                cr_sda <= 1'b0;
                pr_sda <= 1'b0;
            end
        else
            begin
                cr_scl <= I_SCL;
                pr_scl <= cr_scl;
                cr_sda <= sda;
                pr_sda <= cr_sda;
            end
    end

//-------------------------------------------------------------------------- 
    def_freq_i2c
         #(
         .FPGA_CLK(FPGA_CLK),
         .I2C_CLK(I2C_CLK)
        ) 
    def_freq_i2c    
		  (
         .CLK(CLK), 
         .RST_n(RST_n),
         .I_SCL(I_SCL), 
         .I_RS_IO_SCL(rs_scl),
         .I_FL_IO_SCL(fl_scl),         
         .O_MDL_LW_IO_SCL(mdl_lw_io_scl),
         .O_MDL_HG_IO_SCL(mdl_hg_io_scl)
        );
   
//--------------------------------------------------------------------------     
    slv_i2c_fsm
        #(.DATA_SZ(DATA_SZ))
    slv_i2c_fsm
        (
         .CLK(CLK), 
         .RST_n(RST_n), 
         .I_SCL(I_SCL), 
         .I_SDA(sda), 
         .I_RS_IO_SCL(rs_scl), 
         .I_FL_IO_SCL(fl_scl), 
         .I_RS_IO_SDA(rs_sda), 
         .I_FL_IO_SDA(fl_sda), 
         .I_ACK(I_ACK), 
         .I_MDL_LW_IO_SCL(mdl_lw_io_scl), 
         .I_DATA_WR(I_DATA_WR),
         .O_ADDR_SLV(O_ADDR_SLV), 
         .O_RW(O_RW), 
         .O_DATA_RD(O_DATA_RD), 
         .O_SDA(sda_out),
         .O_BUSY(O_BUSY),
         .O_DATA_VL(O_DATA_VL),
         .O_ADDR_REG(O_ADDR_REG),
         .O_CH_CNCT(O_CH_CNCT)
        );        
      
        
        
`ifdef COCOTB_SIM
initial begin
  $dumpfile ("top_slv_i2c.vcd");
  $dumpvars (0, top_slv_i2c);
  #1;
end
`endif
 
endmodule

testbench/top_slv_i2c.vcd
$date
	Fri Oct 08 12:05:02 2021
$end
$version
	Icarus Verilog
$end
$timescale
	1ps
$end
$scope module top_slv_i2c $end
$var wire 1 ! CLK $end
$var wire 1 " I_ACK $end
$var wire 8 # I_DATA_WR [7:0] $end
$var wire 1 $ I_SCL $end
$var wire 1 % RST_n $end
$var wire 1 & fl_scl $end
$var wire 1 ' fl_sda $end
$var wire 1 ( rs_scl $end
$var wire 1 ) rs_sda $end
$var wire 1 * sda $end
$var wire 1 + sda_out $end
$var wire 1 , mdl_lw_io_scl $end
$var wire 1 - mdl_hg_io_scl $end
$var wire 1 . O_RW $end
$var wire 1 / O_DATA_VL $end
$var wire 8 0 O_DATA_RD [7:0] $end
$var wire 1 1 O_CH_CNCT $end
$var wire 1 2 O_BUSY $end
$var wire 7 3 O_ADDR_SLV [6:0] $end
$var wire 8 4 O_ADDR_REG [7:0] $end
$var wire 1 5 IO_SDA $end
$var reg 1 6 cr_scl $end
$var reg 1 7 cr_sda $end
$var reg 1 8 pr_scl $end
$var reg 1 9 pr_sda $end
$scope module def_freq_i2c $end
$var wire 1 ! CLK $end
$var wire 1 & I_FL_IO_SCL $end
$var wire 1 ( I_RS_IO_SCL $end
$var wire 1 $ I_SCL $end
$var wire 1 % RST_n $end
$var wire 1 : en_str $end
$var reg 1 - O_MDL_HG_IO_SCL $end
$var reg 1 , O_MDL_LW_IO_SCL $end
$var reg 9 ; cnt [8:0] $end
$var reg 9 < sv_cnt [8:0] $end
$upscope $end
$scope module slv_i2c_fsm $end
$var wire 1 ! CLK $end
$var wire 1 " I_ACK $end
$var wire 8 = I_DATA_WR [7:0] $end
$var wire 1 & I_FL_IO_SCL $end
$var wire 1 ' I_FL_IO_SDA $end
$var wire 1 , I_MDL_LW_IO_SCL $end
$var wire 1 ( I_RS_IO_SCL $end
$var wire 1 ) I_RS_IO_SDA $end
$var wire 1 $ I_SCL $end
$var wire 1 * I_SDA $end
$var wire 1 % RST_n $end
$var reg 8 > O_ADDR_REG [7:0] $end
$var reg 7 ? O_ADDR_SLV [6:0] $end
$var reg 1 2 O_BUSY $end
$var reg 1 1 O_CH_CNCT $end
$var reg 8 @ O_DATA_RD [7:0] $end
$var reg 1 / O_DATA_VL $end
$var reg 1 . O_RW $end
$var reg 1 + O_SDA $end
$var reg 1 A ack_from_slave $end
$var reg 8 B addr_reg_offset [7:0] $end
$var reg 8 C buff_rd [7:0] $end
$var reg 8 D buff_wr [7:0] $end
$var reg 4 E cnt_bit_data [3:0] $end
$var reg 8 F comm_slv [7:0] $end
$var reg 1 G go $end
$var reg 1 H nx_ack_from_slave $end
$var reg 8 I nx_addr_reg_offset [7:0] $end
$var reg 8 J nx_buff_rd [7:0] $end
$var reg 8 K nx_buff_wr [7:0] $end
$var reg 4 L nx_cnt_bit_data [3:0] $end
$var reg 8 M nx_comm_slv [7:0] $end
$var reg 1 N nx_go $end
$var reg 8 O nx_o_addr_reg [7:0] $end
$var reg 7 P nx_o_addr_slv [6:0] $end
$var reg 1 Q nx_o_busy $end
$var reg 1 R nx_o_ch_cnct $end
$var reg 8 S nx_o_data_rd [7:0] $end
$var reg 1 T nx_o_data_vl $end
$var reg 1 U nx_o_rw $end
$var reg 1 V nx_o_sda $end
$var reg 8 W nx_pr_addr_reg [7:0] $end
$var reg 8 X nx_pr_comm_slv [7:0] $end
$var reg 9 Y nx_st [8:0] $end
$var reg 8 Z pr_addr_reg [7:0] $end
$var reg 8 [ pr_comm_slv [7:0] $end
$var reg 9 \ st [8:0] $end
$upscope $end
$upscope $end
$enddefinitions $end
#0
$dumpvars
b0 \
b0 [
bx Z
b0 Y
b0 X
bx W
1V
xU
0T
bx S
xR
0Q
bx P
bx O
xN
bx M
bx L
bx K
bx J
bx I
xH
xG
bx F
bx E
bx D
bx C
bx B
xA
bx @
bx ?
bx >
bz =
bx <
bx ;
x:
x9
x8
x7
z6
z5
bx 4
bx 3
02
x1
bx 0
0/
x.
x-
x,
1+
z*
x)
x(
x'
x&
1%
z$
bz #
z"
1!
$end
#10000
0'
0)
0&
0(
1H
b0 I
b0 W
0R
b0 O
b0 K
0N
b0 M
0U
b0 P
b0 S
b0 L
b0 J
0:
09
07
08
06
1A
b0 B
b0 Z
01
b0 4
b0 >
b0 D
0G
b0 F
0.
b0 3
b0 ?
b0 0
b0 @
b0 E
b0 C
0-
0,
b0 <
b0 ;
0%
0!
#20000
1!
#30000
0!
#40000
1!
#50000
1%
1$
1*
15
0!
#60000
1)
1(
b1 ;
17
16
1!
#70000
0!
#80000
0)
0(
19
18
b0 ;
1!
#90000
0*
05
0!
#100000
b1 Y
1Q
1'
b1 ;
07
1!
#110000
0!
#120000
0'
09
12
b1 \
b10 ;
1!
#130000
0!
#140000
b11 ;
1!
#150000
0!
#160000
b100 ;
1!
#170000
0!
#180000
b101 ;
1!
#190000
0!
#200000
b110 ;
1!
#210000
0!
#220000
b111 ;
1!
#230000
0!
#240000
b1000 ;
1!
#250000
0!
#260000
b1001 ;
1!
#270000
0!
#280000
b1010 ;
1!
#290000
0!
#300000
b1011 ;
1!
#310000
0!
#320000
b1100 ;
1!
#330000
0!
#340000
b1101 ;
1!
#350000
0!
#360000
b1110 ;
1!
#370000
0!
#380000
b1111 ;
1!
#390000
0!
#400000
b10000 ;
1!
#410000
0!
#420000
b10001 ;
1!
#430000
0!
#440000
b10010 ;
1!
#450000
0!
#460000
b10011 ;
1!
#470000
0!
#480000
b10100 ;
1!
#490000
0!
#500000
b10101 ;
1!
#510000
0!
#520000
b10110 ;
1!
#530000
0!
#540000
b10111 ;
1!
#550000
0!
#560000
b11000 ;
1!
#570000
0!
#580000
b11001 ;
1!
#590000
0!
#600000
b11010 ;
1!
#610000
0!
#620000
b11011 ;
1!
#630000
0!
#640000
b11100 ;
1!
#650000
0!
#660000
b11101 ;
1!
#670000
0!
#680000
b11110 ;
1!
#690000
0!
#700000
b11111 ;
1!
#710000
0!
#720000
b100000 ;
1!
#730000
0!
#740000
b100001 ;
1!
#750000
0!
#760000
b100010 ;
1!
#770000
0!
#780000
b100011 ;
1!
#790000
0!
#800000
b100100 ;
1!
#810000
0!
#820000
b100101 ;
1!
#830000
0!
#840000
b100110 ;
1!
#850000
0!
#860000
b100111 ;
1!
#870000
0!
#880000
b101000 ;
1!
#890000
0!
#900000
b101001 ;
1!
#910000
0!
#920000
b101010 ;
1!
#930000
0!
#940000
b101011 ;
1!
#950000
0!
#960000
b101100 ;
1!
#970000
0!
#980000
b101101 ;
1!
#990000
0!
#1000000
b101110 ;
1!
#1010000
0!
#1020000
b101111 ;
1!
#1030000
0!
#1040000
b110000 ;
1!
#1050000
0!
#1060000
b110001 ;
1!
#1070000
0!
#1080000
b110010 ;
1!
#1090000
0!
#1100000
b110011 ;
1!
#1110000
0!
#1120000
b110100 ;
1!
#1130000
0!
#1140000
b110101 ;
1!
#1150000
0!
#1160000
b110110 ;
1!
#1170000
0!
#1180000
b110111 ;
1!
#1190000
0!
#1200000
b111000 ;
1!
#1210000
0!
#1220000
b111001 ;
1!
#1230000
0!
#1240000
b111010 ;
1!
#1250000
0!
#1260000
b111011 ;
1!
#1270000
0!
#1280000
b111100 ;
1!
#1290000
0!
#1300000
b111101 ;
1!
#1310000
0!
#1320000
b111110 ;
1!
#1330000
0!
#1340000
b111111 ;
1!
#1350000
0!
#1360000
b1000000 ;
1!
#1370000
0!
#1380000
b1000001 ;
1!
#1390000
0!
#1400000
b1000010 ;
1!
#1410000
0!
#1420000
b1000011 ;
1!
#1430000
0!
#1440000
b1000100 ;
1!
#1450000
0!
#1460000
b1000101 ;
1!
#1470000
0!
#1480000
b1000110 ;
1!
#1490000
0!
#1500000
b1000111 ;
1!
#1510000
0!
#1520000
b1001000 ;
1!
#1530000
0!
#1540000
b1001001 ;
1!
#1550000
0!
#1560000
b1001010 ;
1!
#1570000
0!
#1580000
b1001011 ;
1!
#1590000
0!
#1600000
b1001100 ;
1!
#1610000
0!
#1620000
b1001101 ;
1!
#1630000
0!
#1640000
b1001110 ;
1!
#1650000
0!
#1660000
b1001111 ;
1!
#1670000
0!
#1680000
b1010000 ;
1!
#1690000
0!
#1700000
b1010001 ;
1!
#1710000
0!
#1720000
b1010010 ;
1!
#1730000
0!
#1740000
b1010011 ;
1!
#1750000
0!
#1760000
b1010100 ;
1!
#1770000
0!
#1780000
b1010101 ;
1!
#1790000
0!
#1800000
b1010110 ;
1!
#1810000
0!
#1820000
b1010111 ;
1!
#1830000
0!
#1840000
b1011000 ;
1!
#1850000
0!
#1860000
b1011001 ;
1!
#1870000
0!
#1880000
b1011010 ;
1!
#1890000
0!
#1900000
b1011011 ;
1!
#1910000
0!
#1920000
b1011100 ;
1!
#1930000
0!
#1940000
b1011101 ;
1!
#1950000
0!
#1960000
b1011110 ;
1!
#1970000
0!
#1980000
b1011111 ;
1!
#1990000
0!
#2000000
b1100000 ;
1!
#2010000
0!
#2020000
b1100001 ;
1!
#2030000
0!
#2040000
b1100010 ;
1!
#2050000
0!
#2060000
b1100011 ;
1!
#2070000
0!
#2080000
b1100100 ;
1!
#2090000
0!
#2100000
b1100101 ;
1!
#2110000
0!
#2120000
b1100110 ;
1!
#2130000
0!
#2140000
b1100111 ;
1!
#2150000
0!
#2160000
b1101000 ;
1!
#2170000
0!
#2180000
b1101001 ;
1!
#2190000
0!
#2200000
b1101010 ;
1!
#2210000
0!
#2220000
b1101011 ;
1!
#2230000
0!
#2240000
b1101100 ;
1!
#2250000
0!
#2260000
b1101101 ;
1!
#2270000
0!
#2280000
b1101110 ;
1!
#2290000
0!
#2300000
b1101111 ;
1!
#2310000
0!
#2320000
b1110000 ;
1!
#2330000
0!
#2340000
b1110001 ;
1!
#2350000
0!
#2360000
b1110010 ;
1!
#2370000
0!
#2380000
b1110011 ;
1!
#2390000
0!
#2400000
b1110100 ;
1!
#2410000
0!
#2420000
b1110101 ;
1!
#2430000
0!
#2440000
b1110110 ;
1!
#2450000
0!
#2460000
b1110111 ;
1!
#2470000
0!
#2480000
b1111000 ;
1!
#2490000
0!
#2500000
b1111001 ;
1!
#2510000
0!
#2520000
b1111010 ;
1!
#2530000
0!
#2540000
b1111011 ;
1!
#2550000
0!
#2560000
b1111100 ;
1!
#2570000
0!
#2580000
b1111101 ;
1!
#2590000
0$
0!
#2600000
1&
06
b1111110 ;
1!
#2610000
0!
#2620000
0&
b1111110 <
b0 ;
08
1!
#2630000
0!
#2640000
b1 ;
1!
#2650000
0!
#2660000
b10 ;
1!
#2670000
0!
#2680000
b11 ;
1!
#2690000
0!
#2700000
b100 ;
1!
#2710000
0!
#2720000
b101 ;
1!
#2730000
0!
#2740000
b110 ;
1!
#2750000
0!
#2760000
b111 ;
1!
#2770000
0!
#2780000
b1000 ;
1!
#2790000
0!
#2800000
b1001 ;
1!
#2810000
0!
#2820000
b1010 ;
1!
#2830000
0!
#2840000
b1011 ;
1!
#2850000
0!
#2860000
b1100 ;
1!
#2870000
0!
#2880000
b1101 ;
1!
#2890000
0!
#2900000
b1110 ;
1!
#2910000
0!
#2920000
b1111 ;
1!
#2930000
0!
#2940000
b10000 ;
1!
#2950000
0!
#2960000
b10001 ;
1!
#2970000
0!
#2980000
b10010 ;
1!
#2990000
0!
#3000000
b10011 ;
1!
#3010000
0!
#3020000
b10100 ;
1!
#3030000
0!
#3040000
b10101 ;
1!
#3050000
0!
#3060000
b10110 ;
1!
#3070000
0!
#3080000
b10111 ;
1!
#3090000
0!
#3100000
b11000 ;
1!
#3110000
0!
#3120000
b11001 ;
1!
#3130000
0!
#3140000
b11010 ;
1!
#3150000
0!
#3160000
b11011 ;
1!
#3170000
0!
#3180000
b11100 ;
1!
#3190000
0!
#3200000
b11101 ;
1!
#3210000
0!
#3220000
b11110 ;
1!
#3230000
0!
#3240000
b11111 ;
1!
#3250000
0!
#3260000
b100000 ;
1!
#3270000
0!
